odoo8_addon_l10n_it_vat_registries-8.0.3.0.0-nspkg.pth
odoo_addons/l10n_it_vat_registries/README.rst
odoo_addons/l10n_it_vat_registries/__init__.py
odoo_addons/l10n_it_vat_registries/__openerp__.py
odoo_addons/l10n_it_vat_registries/account.py
odoo_addons/l10n_it_vat_registries/account_journal.py
odoo_addons/l10n_it_vat_registries/account_journal_view.xml
odoo_addons/l10n_it_vat_registries/account_tax_registry.py
odoo_addons/l10n_it_vat_registries/account_tax_registry_view.xml
odoo_addons/l10n_it_vat_registries/account_view.xml
odoo_addons/l10n_it_vat_registries/reports.xml
odoo_addons/l10n_it_vat_registries/vat_registry.py
odoo_addons/l10n_it_vat_registries/i18n/es.po
odoo_addons/l10n_it_vat_registries/i18n/it.po
odoo_addons/l10n_it_vat_registries/i18n/l10n_it_vat_registries.pot
odoo_addons/l10n_it_vat_registries/i18n/sl.po
odoo_addons/l10n_it_vat_registries/security/ir.model.access.csv
odoo_addons/l10n_it_vat_registries/security/vat_registry_security.xml
odoo_addons/l10n_it_vat_registries/static/1-tax_iva22indetraibiel40.png
odoo_addons/l10n_it_vat_registries/static/2-taxcode_iva22indetraibile40_imponibile.png
odoo_addons/l10n_it_vat_registries/static/3-tax_iva22indetraibile40_parte_indetraibile.png
odoo_addons/l10n_it_vat_registries/static/4-taxcode_iva22indetraibile40_parte_indetraibile_.png
odoo_addons/l10n_it_vat_registries/static/5-tax_iva22indetraibile40_parte_detraibile.png
odoo_addons/l10n_it_vat_registries/static/6-taxcode_iva22indetraibile40_parte_detraibile.png
odoo_addons/l10n_it_vat_registries/static/description/icon.png
odoo_addons/l10n_it_vat_registries/static/src/css/l10n_it_vat_registries.css
odoo_addons/l10n_it_vat_registries/views/report_registro_iva.xml
odoo_addons/l10n_it_vat_registries/wizard/__init__.py
odoo_addons/l10n_it_vat_registries/wizard/print_registro_iva.py
odoo_addons/l10n_it_vat_registries/wizard/print_registro_iva.xml
odoo8_addon_l10n_it_vat_registries-8.0.3.0.0.dist-info/METADATA
odoo8_addon_l10n_it_vat_registries-8.0.3.0.0.dist-info/WHEEL
odoo8_addon_l10n_it_vat_registries-8.0.3.0.0.dist-info/namespace_packages.txt
odoo8_addon_l10n_it_vat_registries-8.0.3.0.0.dist-info/top_level.txt
odoo8_addon_l10n_it_vat_registries-8.0.3.0.0.dist-info/RECORD
