Metadata-Version: 2.1
Name: odoo8-addon-l10n-it-vat-registries
Version: 8.0.3.0.0
Summary: Italian Localization - VAT Registries
Home-page: http://www.agilebg.com
Author: Agile Business Group, Odoo Community Association (OCA), LinkIt Spa
Author-email: support@odoo-community.org
License: AGPL-3
Platform: UNKNOWN
Classifier: Programming Language :: Python
Classifier: Framework :: Odoo
Classifier: License :: OSI Approved :: GNU Affero General Public License v3
Requires-Python: ~=2.7
Requires-Dist: odoo8-addon-l10n-it-account
Requires-Dist: odoo (<9.0a,>=8.0a)
